{"cameraMode":{"drawMode":0,"name":"Shaded","section":"Shading Mode"},"sceneLighting":true,"audioPlay":false,"sceneViewState":{"m_AlwaysRefresh":false,"showFog":true,"showSkybox":true,"showFlares":true,"showImageEffects":true,"showParticleSystems":true,"showVisualEffectGraphs":true,"m_FxEnabled":true},"in2DMode":false,"pivot":{"x":-533.0160522460938,"y":-147.2158203125,"z":-11.563075065612793},"rotation":{"x":0.10013454407453537,"y":-0.7057803869247437,"z":0.10671353340148926,"w":0.6941482424736023},"size":300.6997375488281,"orthographic":false}